{
  "schema": "deeplus.constitutional-law-catalog/r51f3",
  "baseline": "0.1.2-baseline.r51f3",
  "law_count": 29,
  "laws": [
    {
      "law_id": "OP-ACTOR-014",
      "obligation": "Actor mailboxes preserve sender-to-receiver FIFO without promising global sender order.",
      "normalized_semantic_form": {
        "law_id": "OP-ACTOR-014",
        "modality": "MUST",
        "normalized_obligation": "Actor mailboxes preserve sender-to-receiver FIFO without promising global sender order.",
        "product_execution": "NOT_RUN"
      },
      "fingerprint_sha256": "613330b079ec2f28217952486a517f3316c47c03db91e6c0034e07a403c6e2ca",
      "ratification_decision_id": "R51a1-DD-014",
      "positive_fixture_id": "CF-OP-ACTOR-014-POS",
      "reversal_mutation_id": "constitutional_reversal_13",
      "execution_status": "DESIGN_STATIC_NOT_RUN"
    },
    {
      "law_id": "OP-ACTOR-FIFO-029",
      "obligation": "Preserve FIFO message order within one sender/receiver channel under the minimum mailbox profile.",
      "normalized_semantic_form": {
        "law_id": "OP-ACTOR-FIFO-029",
        "modality": "MUST",
        "normalized_obligation": "Preserve FIFO message order within one sender/receiver channel under the minimum mailbox profile.",
        "product_execution": "NOT_RUN"
      },
      "fingerprint_sha256": "c681d54712461cd51b3ce83ca24706a5f00fba2c85583e3422a46373e658968f",
      "ratification_decision_id": "R51d-DD-029",
      "positive_fixture_id": "CF-OP-ACTOR-FIFO-029-POS",
      "reversal_mutation_id": "constitutional_reversal_28",
      "execution_status": "DESIGN_STATIC_NOT_RUN"
    },
    {
      "law_id": "OP-ASSIGN-003",
      "obligation": "Complete RHS before dropping and replacing the old place value.",
      "normalized_semantic_form": {
        "law_id": "OP-ASSIGN-003",
        "modality": "MUST",
        "normalized_obligation": "Complete RHS before dropping and replacing the old place value.",
        "product_execution": "NOT_RUN"
      },
      "fingerprint_sha256": "6194119cd7888c0d002a963d541b7bd8a58945c09f1e8b3abcdcbfc150b284e6",
      "ratification_decision_id": "R51a1-DD-003",
      "positive_fixture_id": "CF-OP-ASSIGN-003-POS",
      "reversal_mutation_id": "constitutional_reversal_02",
      "execution_status": "DESIGN_STATIC_NOT_RUN"
    },
    {
      "law_id": "OP-CALLABLE-020",
      "obligation": "Preserve callable lifetime, call-right, environment, and behavior responsibility across type checking, API digest, and lowering.",
      "normalized_semantic_form": {
        "law_id": "OP-CALLABLE-020",
        "modality": "MUST",
        "normalized_obligation": "Preserve callable lifetime, call-right, environment, and behavior responsibility across type checking, API digest, and lowering.",
        "product_execution": "NOT_RUN"
      },
      "fingerprint_sha256": "32a709beaf882b72c5fe3db4252199f406c54626d9d8e83bc6a04e517b01d1e6",
      "ratification_decision_id": "R51a1-DD-020",
      "positive_fixture_id": "CF-OP-CALLABLE-020-POS",
      "reversal_mutation_id": "constitutional_reversal_19",
      "execution_status": "DESIGN_STATIC_NOT_RUN"
    },
    {
      "law_id": "OP-CANCEL-012",
      "obligation": "Cancellation is cooperative and never bypasses lexical cleanup.",
      "normalized_semantic_form": {
        "law_id": "OP-CANCEL-012",
        "modality": "MUST",
        "normalized_obligation": "Cancellation is cooperative and never bypasses lexical cleanup.",
        "product_execution": "NOT_RUN"
      },
      "fingerprint_sha256": "a4ae359aea6a72eb00b15428e4af44b189c0ad25788494871efb1ecc55b6bcd7",
      "ratification_decision_id": "R51a1-DD-012",
      "positive_fixture_id": "CF-OP-CANCEL-012-POS",
      "reversal_mutation_id": "constitutional_reversal_11",
      "execution_status": "DESIGN_STATIC_NOT_RUN"
    },
    {
      "law_id": "OP-CLEANUP-021",
      "obligation": "Invoke def#cleanup exactly once for initialized non-moved state, never by direct call, while preserving primary and suppressed failure order.",
      "normalized_semantic_form": {
        "law_id": "OP-CLEANUP-021",
        "modality": "MUST",
        "normalized_obligation": "Invoke def#cleanup exactly once for initialized non-moved state, never by direct call, while preserving primary and suppressed failure order.",
        "product_execution": "NOT_RUN"
      },
      "fingerprint_sha256": "752028e460ca1bd3a9e1bfb0843134819bdf81bf96225f4ea01b6a25c09053a6",
      "ratification_decision_id": "R51a1-DD-021",
      "positive_fixture_id": "CF-OP-CLEANUP-021-POS",
      "reversal_mutation_id": "constitutional_reversal_20",
      "execution_status": "DESIGN_STATIC_NOT_RUN"
    },
    {
      "law_id": "OP-CONSTRUCT-004",
      "obligation": "Initialize construction fields in row/source order and roll back completed fields in reverse order.",
      "normalized_semantic_form": {
        "law_id": "OP-CONSTRUCT-004",
        "modality": "MUST",
        "normalized_obligation": "Initialize construction fields in row/source order and roll back completed fields in reverse order.",
        "product_execution": "NOT_RUN"
      },
      "fingerprint_sha256": "d31d37461069743ae82bfd3b94c4fc3c95aa18b6a427e54f13d49fabfd424802",
      "ratification_decision_id": "R51a1-DD-004",
      "positive_fixture_id": "CF-OP-CONSTRUCT-004-POS",
      "reversal_mutation_id": "constitutional_reversal_03",
      "execution_status": "DESIGN_STATIC_NOT_RUN"
    },
    {
      "law_id": "OP-DYNAMIC-UNIT-027",
      "obligation": "Activate dynamic unit conversion through stdlib/provider profile, provider identity and complete policy; never through a source Preview gate.",
      "normalized_semantic_form": {
        "law_id": "OP-DYNAMIC-UNIT-027",
        "modality": "MUST",
        "normalized_obligation": "Activate dynamic unit conversion through stdlib/provider profile, provider identity and complete policy; never through a source Preview gate.",
        "product_execution": "NOT_RUN"
      },
      "fingerprint_sha256": "ad7af2e769c11a5af0e99d111703b8ab94c10752b3dbc45805e864e9a07f7118",
      "ratification_decision_id": "R51d-DD-027",
      "positive_fixture_id": "CF-OP-DYNAMIC-UNIT-027-POS",
      "reversal_mutation_id": "constitutional_reversal_26",
      "execution_status": "DESIGN_STATIC_NOT_RUN"
    },
    {
      "law_id": "OP-ENTRY-010",
      "obligation": "Select exactly one admitted entry and project host status only after cleanup.",
      "normalized_semantic_form": {
        "law_id": "OP-ENTRY-010",
        "modality": "MUST",
        "normalized_obligation": "Select exactly one admitted entry and project host status only after cleanup.",
        "product_execution": "NOT_RUN"
      },
      "fingerprint_sha256": "4cb5b0cfd84fe0a30f6728a936b3ae10824b98e7e8e8dd880539491c8b49661e",
      "ratification_decision_id": "R51a1-DD-010",
      "positive_fixture_id": "CF-OP-ENTRY-010-POS",
      "reversal_mutation_id": "constitutional_reversal_09",
      "execution_status": "DESIGN_STATIC_NOT_RUN"
    },
    {
      "law_id": "OP-EVAL-001",
      "obligation": "Evaluate subexpressions exactly once in source order.",
      "normalized_semantic_form": {
        "law_id": "OP-EVAL-001",
        "modality": "MUST",
        "normalized_obligation": "Evaluate subexpressions exactly once in source order.",
        "product_execution": "NOT_RUN"
      },
      "fingerprint_sha256": "a391e011d59399b4c7229d73106ad38b8cfd527e4706e1f72941d81c8bf051f9",
      "ratification_decision_id": "R51a1-DD-001",
      "positive_fixture_id": "CF-OP-EVAL-001-POS",
      "reversal_mutation_id": "constitutional_reversal_00",
      "execution_status": "DESIGN_STATIC_NOT_RUN"
    },
    {
      "law_id": "OP-EVIDENCE-022",
      "obligation": "Resolve a root conformance evidence selector to exactly one visible coherent nominal conformance without constructing a first-class witness value.",
      "normalized_semantic_form": {
        "law_id": "OP-EVIDENCE-022",
        "modality": "MUST",
        "normalized_obligation": "Resolve a root conformance evidence selector to exactly one visible coherent nominal conformance without constructing a first-class witness value.",
        "product_execution": "NOT_RUN"
      },
      "fingerprint_sha256": "8d5a210ae05f9877d7f51efd38cbe0147e022fde34e2f85d7a235e172c600ea4",
      "ratification_decision_id": "R51a1-DD-022",
      "positive_fixture_id": "CF-OP-EVIDENCE-022-POS",
      "reversal_mutation_id": "constitutional_reversal_21",
      "execution_status": "DESIGN_STATIC_NOT_RUN"
    },
    {
      "law_id": "OP-FAIL-011",
      "obligation": "Retain the first escaping failure and append cleanup failures in execution order.",
      "normalized_semantic_form": {
        "law_id": "OP-FAIL-011",
        "modality": "MUST",
        "normalized_obligation": "Retain the first escaping failure and append cleanup failures in execution order.",
        "product_execution": "NOT_RUN"
      },
      "fingerprint_sha256": "63e17fb9d39223ce4ee60cbc48f7c7a75dcd29203005bd4a27da2bf7b5347ebd",
      "ratification_decision_id": "R51a1-DD-011",
      "positive_fixture_id": "CF-OP-FAIL-011-POS",
      "reversal_mutation_id": "constitutional_reversal_10",
      "execution_status": "DESIGN_STATIC_NOT_RUN"
    },
    {
      "law_id": "OP-GUARD-017",
      "obligation": "Evaluate every guard left-to-right once before ownership commit or payload evaluation; a false guard evaluates no payload.",
      "normalized_semantic_form": {
        "law_id": "OP-GUARD-017",
        "modality": "MUST",
        "normalized_obligation": "Evaluate every guard left-to-right once before ownership commit or payload evaluation; a false guard evaluates no payload.",
        "product_execution": "NOT_RUN"
      },
      "fingerprint_sha256": "e984187fa2f1d5cbd44025a2188575b6de3326ae01d3fdbbfd579a69659690f8",
      "ratification_decision_id": "R51a1-DD-017",
      "positive_fixture_id": "CF-OP-GUARD-017-POS",
      "reversal_mutation_id": "constitutional_reversal_16",
      "execution_status": "DESIGN_STATIC_NOT_RUN"
    },
    {
      "law_id": "OP-HASH-ROLE-026",
      "obligation": "Reject a physical line break between # and a role word while admitting only same-line horizontal trivia.",
      "normalized_semantic_form": {
        "law_id": "OP-HASH-ROLE-026",
        "modality": "MUST",
        "normalized_obligation": "Reject a physical line break between # and a role word while admitting only same-line horizontal trivia.",
        "product_execution": "NOT_RUN"
      },
      "fingerprint_sha256": "17a7b5edfb0c2e12f57eb66a1c40328ddf9c163a95f6d4a1c4978f9413d260f1",
      "ratification_decision_id": "R51d-DD-026",
      "positive_fixture_id": "CF-OP-HASH-ROLE-026-POS",
      "reversal_mutation_id": "constitutional_reversal_25",
      "execution_status": "DESIGN_STATIC_NOT_RUN"
    },
    {
      "law_id": "OP-INIT-009",
      "obligation": "Evaluate library static lets in deterministic dependency order and commit each once.",
      "normalized_semantic_form": {
        "law_id": "OP-INIT-009",
        "modality": "MUST",
        "normalized_obligation": "Evaluate library static lets in deterministic dependency order and commit each once.",
        "product_execution": "NOT_RUN"
      },
      "fingerprint_sha256": "066fa08e60582994c463ce18a5a82750311f6fe7d68b016889d0b1f478db6d49",
      "ratification_decision_id": "R51a1-DD-009",
      "positive_fixture_id": "CF-OP-INIT-009-POS",
      "reversal_mutation_id": "constitutional_reversal_08",
      "execution_status": "DESIGN_STATIC_NOT_RUN"
    },
    {
      "law_id": "OP-LOCAL-OPTION-007",
      "obligation": "Insert at most one outer some only for an independently fixed local target.",
      "normalized_semantic_form": {
        "law_id": "OP-LOCAL-OPTION-007",
        "modality": "MUST",
        "normalized_obligation": "Insert at most one outer some only for an independently fixed local target.",
        "product_execution": "NOT_RUN"
      },
      "fingerprint_sha256": "32870aeb0c14b8d14913feeade870500a33d74aceabfe54e0ca7d85fb158fe48",
      "ratification_decision_id": "R51a1-DD-007",
      "positive_fixture_id": "CF-OP-LOCAL-OPTION-007-POS",
      "reversal_mutation_id": "constitutional_reversal_06",
      "execution_status": "DESIGN_STATIC_NOT_RUN"
    },
    {
      "law_id": "OP-LOCAL-VALUE-018",
      "obligation": "A multi-statement local value body produces a value with local ret on every reachable normal path.",
      "normalized_semantic_form": {
        "law_id": "OP-LOCAL-VALUE-018",
        "modality": "MUST",
        "normalized_obligation": "A multi-statement local value body produces a value with local ret on every reachable normal path.",
        "product_execution": "NOT_RUN"
      },
      "fingerprint_sha256": "1e36377d6ce8a941ac0f6487c411ec62a09db20ca37249b2d185a2b9a5d09a84",
      "ratification_decision_id": "R51a1-DD-018",
      "positive_fixture_id": "CF-OP-LOCAL-VALUE-018-POS",
      "reversal_mutation_id": "constitutional_reversal_17",
      "execution_status": "DESIGN_STATIC_NOT_RUN"
    },
    {
      "law_id": "OP-LOOP-019",
      "obligation": "Only the final loop transfer target executes and observes its outcome handler after intermediate cleanup.",
      "normalized_semantic_form": {
        "law_id": "OP-LOOP-019",
        "modality": "MUST",
        "normalized_obligation": "Only the final loop transfer target executes and observes its outcome handler after intermediate cleanup.",
        "product_execution": "NOT_RUN"
      },
      "fingerprint_sha256": "1a9e5eeaa80f703028492ee71d0aedc38265eb83e50d94624bd33622412f35e0",
      "ratification_decision_id": "R51a1-DD-019",
      "positive_fixture_id": "CF-OP-LOOP-019-POS",
      "reversal_mutation_id": "constitutional_reversal_18",
      "execution_status": "DESIGN_STATIC_NOT_RUN"
    },
    {
      "law_id": "OP-NAMED-REST-023",
      "obligation": "Keep declaration-side *** collection distinct from call-side ** named unfolding in parsing, typing, and API residue.",
      "normalized_semantic_form": {
        "law_id": "OP-NAMED-REST-023",
        "modality": "MUST",
        "normalized_obligation": "Keep declaration-side *** collection distinct from call-side ** named unfolding in parsing, typing, and API residue.",
        "product_execution": "NOT_RUN"
      },
      "fingerprint_sha256": "1ebb2f0d7478958c2deea1b0540567a733bf26e89a3312d3bf8efb06ac0a92d1",
      "ratification_decision_id": "R51a1-DD-023",
      "positive_fixture_id": "CF-OP-NAMED-REST-023-POS",
      "reversal_mutation_id": "constitutional_reversal_22",
      "execution_status": "DESIGN_STATIC_NOT_RUN"
    },
    {
      "law_id": "OP-NUMARR-016",
      "obligation": "NumericArray operations preserve source evaluation order, shape checks, and explicit allocation/authority effects.",
      "normalized_semantic_form": {
        "law_id": "OP-NUMARR-016",
        "modality": "MUST",
        "normalized_obligation": "NumericArray operations preserve source evaluation order, shape checks, and explicit allocation/authority effects.",
        "product_execution": "NOT_RUN"
      },
      "fingerprint_sha256": "ca275326fc4aaf75db918e06737e28b92ef9eb72e6893975668ce21748cf66b9",
      "ratification_decision_id": "R51a1-DD-016",
      "positive_fixture_id": "CF-OP-NUMARR-016-POS",
      "reversal_mutation_id": "constitutional_reversal_15",
      "execution_status": "DESIGN_STATIC_NOT_RUN"
    },
    {
      "law_id": "OP-NUMERIC-015",
      "obligation": "Numeric operations follow their declared checked/static responsibility without hidden widening.",
      "normalized_semantic_form": {
        "law_id": "OP-NUMERIC-015",
        "modality": "MUST",
        "normalized_obligation": "Numeric operations follow their declared checked/static responsibility without hidden widening.",
        "product_execution": "NOT_RUN"
      },
      "fingerprint_sha256": "903fde172e8fce4a4cdb2d8d7a926012aeea23d26af3307c2f9983253693fb53",
      "ratification_decision_id": "R51a1-DD-015",
      "positive_fixture_id": "CF-OP-NUMERIC-015-POS",
      "reversal_mutation_id": "constitutional_reversal_14",
      "execution_status": "DESIGN_STATIC_NOT_RUN"
    },
    {
      "law_id": "OP-OPTION-006",
      "obligation": "Evaluate Option coalescing lhs once and rhs only for none.",
      "normalized_semantic_form": {
        "law_id": "OP-OPTION-006",
        "modality": "MUST",
        "normalized_obligation": "Evaluate Option coalescing lhs once and rhs only for none.",
        "product_execution": "NOT_RUN"
      },
      "fingerprint_sha256": "652c52b131b34d6cbe3b106db3f53ef4b29e5c86aff28340aae246b276d47944",
      "ratification_decision_id": "R51a1-DD-006",
      "positive_fixture_id": "CF-OP-OPTION-006-POS",
      "reversal_mutation_id": "constitutional_reversal_05",
      "execution_status": "DESIGN_STATIC_NOT_RUN"
    },
    {
      "law_id": "OP-OPTION-COALESCE-028",
      "obligation": "Evaluate the Option coalescing fallback only when the left operand is none.",
      "normalized_semantic_form": {
        "law_id": "OP-OPTION-COALESCE-028",
        "modality": "MUST",
        "normalized_obligation": "Evaluate the Option coalescing fallback only when the left operand is none.",
        "product_execution": "NOT_RUN"
      },
      "fingerprint_sha256": "04ce1976a4e3618b333493eeb2aef5a661fca646fd9762138176b6f6bc2777e2",
      "ratification_decision_id": "R51d-DD-028",
      "positive_fixture_id": "CF-OP-OPTION-COALESCE-028-POS",
      "reversal_mutation_id": "constitutional_reversal_27",
      "execution_status": "DESIGN_STATIC_NOT_RUN"
    },
    {
      "law_id": "OP-PROJECT-005",
      "obligation": "Evaluate a projection source once and project in target-row order under declared ownership.",
      "normalized_semantic_form": {
        "law_id": "OP-PROJECT-005",
        "modality": "MUST",
        "normalized_obligation": "Evaluate a projection source once and project in target-row order under declared ownership.",
        "product_execution": "NOT_RUN"
      },
      "fingerprint_sha256": "240a3dcba887b38d4e16d66a51b927f143646f2673231ca0c7f614ca1a0c051d",
      "ratification_decision_id": "R51a1-DD-005",
      "positive_fixture_id": "CF-OP-PROJECT-005-POS",
      "reversal_mutation_id": "constitutional_reversal_04",
      "execution_status": "DESIGN_STATIC_NOT_RUN"
    },
    {
      "law_id": "OP-RAW-STRING-025",
      "obligation": "Raw String Phase A preserves exact body scalars and performs no escape or interpolation interpretation.",
      "normalized_semantic_form": {
        "law_id": "OP-RAW-STRING-025",
        "modality": "MUST",
        "normalized_obligation": "Raw String Phase A preserves exact body scalars and performs no escape or interpolation interpretation.",
        "product_execution": "NOT_RUN"
      },
      "fingerprint_sha256": "22ea4cc9f99c0784ea543fef05848a0e7bfda8e05eb22cb6ba1055547a678acc",
      "ratification_decision_id": "R51d-DD-025",
      "positive_fixture_id": "CF-OP-RAW-STRING-025-POS",
      "reversal_mutation_id": "constitutional_reversal_24",
      "execution_status": "DESIGN_STATIC_NOT_RUN"
    },
    {
      "law_id": "OP-RIGHTWARD-BIND-024",
      "obligation": "Normalize rightward local binding to ordinary let/var before semantic AST/HIR and MIR; evaluate once and commit only after success.",
      "normalized_semantic_form": {
        "law_id": "OP-RIGHTWARD-BIND-024",
        "modality": "MUST",
        "normalized_obligation": "Normalize rightward local binding to ordinary let/var before semantic AST/HIR and MIR; evaluate once and commit only after success.",
        "product_execution": "NOT_RUN"
      },
      "fingerprint_sha256": "0d01ef38c583ac9958f54d1c195c82da1bdc8fc2cebce5f447ee8b8ae3856d1e",
      "ratification_decision_id": "R51d-DD-024",
      "positive_fixture_id": "CF-OP-RIGHTWARD-BIND-024-POS",
      "reversal_mutation_id": "constitutional_reversal_23",
      "execution_status": "DESIGN_STATIC_NOT_RUN"
    },
    {
      "law_id": "OP-TASK-013",
      "obligation": "A task scope joins or cancels all owned children before exit.",
      "normalized_semantic_form": {
        "law_id": "OP-TASK-013",
        "modality": "MUST",
        "normalized_obligation": "A task scope joins or cancels all owned children before exit.",
        "product_execution": "NOT_RUN"
      },
      "fingerprint_sha256": "7c82eebe213b894b7ab10f91a851009db91dd2b85e26da0ab76082775fb07722",
      "ratification_decision_id": "R51a1-DD-013",
      "positive_fixture_id": "CF-OP-TASK-013-POS",
      "reversal_mutation_id": "constitutional_reversal_12",
      "execution_status": "DESIGN_STATIC_NOT_RUN"
    },
    {
      "law_id": "OP-TEMP-002",
      "obligation": "Drop full-expression temporaries in reverse completion order.",
      "normalized_semantic_form": {
        "law_id": "OP-TEMP-002",
        "modality": "MUST",
        "normalized_obligation": "Drop full-expression temporaries in reverse completion order.",
        "product_execution": "NOT_RUN"
      },
      "fingerprint_sha256": "e8881f7739df7ede8317a7596955b695ff2b98ab5cfce1901033c49550ca9658",
      "ratification_decision_id": "R51a1-DD-002",
      "positive_fixture_id": "CF-OP-TEMP-002-POS",
      "reversal_mutation_id": "constitutional_reversal_01",
      "execution_status": "DESIGN_STATIC_NOT_RUN"
    },
    {
      "law_id": "OP-UNIT-008",
      "obligation": "Normalize unit dimensions and rational scale exactly before equality or conversion.",
      "normalized_semantic_form": {
        "law_id": "OP-UNIT-008",
        "modality": "MUST",
        "normalized_obligation": "Normalize unit dimensions and rational scale exactly before equality or conversion.",
        "product_execution": "NOT_RUN"
      },
      "fingerprint_sha256": "6938b86b72637056554431fd286c802f351fa96619168b687f5bba7a7eb6a329",
      "ratification_decision_id": "R51a1-DD-008",
      "positive_fixture_id": "CF-OP-UNIT-008-POS",
      "reversal_mutation_id": "constitutional_reversal_07",
      "execution_status": "DESIGN_STATIC_NOT_RUN"
    }
  ],
  "fixture_registry": "tests/fixtures/imported/constitutional-law-fixtures.json",
  "constitutional_digest_sha256": "106384b40b8605e5f71a0f301dfd64b484b85f7ab3fc9b0e431907b26839b5eb",
  "digest_canonicalization": "SHA-256 over canonical UTF-8 JSON of laws sorted in catalog order with object keys sorted and no insignificant whitespace",
  "mutation_policy": "each normalized law has a reversal plus a coordinated same-wrong attack; changing a ratified law requires a new decision id and detached trust anchor",
  "product_runtime": "NOT_RUN",
  "integrated_checker": "NOT_RUN"
}
